bbstrader-2.0.6.dist-info/WHEEL
bbstrader-2.0.6.dist-info/entry_points.txt
bbstrader-2.0.6.dist-info/METADATA
bbstrader-2.0.6.dist-info/RECORD
bbstrader-2.0.6.dist-info/licenses/LICENSE
bbstrader.libs/libgcc_s-fd2fd9f2.so.1
bbstrader.libs/libstdc++-2f15e5cf.so.6.0.30
bbstrader/scripts.py
bbstrader/__main__.py
bbstrader/compat.py
bbstrader/config.py
bbstrader/__init__.py
bbstrader/api/client.cpython-312-x86_64-linux-musl.so
bbstrader/api/handlers.py
bbstrader/api/client.pyi
bbstrader/api/__init__.py
bbstrader/models/optimization.py
bbstrader/models/nlp.py
bbstrader/models/__init__.py
bbstrader/assets/bbstrader.ico
bbstrader/assets/bbs_.png
bbstrader/assets/qs_metrics_1.png
bbstrader/assets/bbstrader.png
bbstrader/metatrader/_copier.py
bbstrader/metatrader/utils.py
bbstrader/metatrader/rates.py
bbstrader/metatrader/risk.py
bbstrader/metatrader/trade.py
bbstrader/metatrader/account.py
bbstrader/metatrader/copier.py
bbstrader/metatrader/__init__.py
bbstrader/metatrader/broker.py
bbstrader/core/data.py
bbstrader/core/strategy.py
bbstrader/core/__init__.py
bbstrader/btengine/event.py
bbstrader/btengine/data.py
bbstrader/btengine/strategy.py
bbstrader/btengine/execution.py
bbstrader/btengine/performance.py
bbstrader/btengine/backtest.py
bbstrader/btengine/__init__.py
bbstrader/btengine/portfolio.py
bbstrader/trading/utils.py
bbstrader/trading/strategy.py
bbstrader/trading/execution.py
bbstrader/trading/__init__.py
