Metadata-Version: 2.4
Name: bbstrader
Version: 2.0.6
Summary: Simplified Investment & Trading Toolkit with Python & C++
Keywords: Finance,Toolkit,Financial,Analysis,Fundamental,Quantitative,Database,Equities,Currencies,Economics,ETFs,Funds,Indices,Moneymarkets,Commodities,Futures,CFDs,Derivatives,Trading,Investing,Portfolio,Optimization,Performance
Author-Email: Bertin Balouki SIMYELI <bertin@bbs-trading.com>
Maintainer-Email: Bertin Balouki SIMYELI <bertin@bbs-trading.com>
License-Expression: MIT
Classifier: Development Status :: 5 - Production/Stable
Classifier: Intended Audience :: Developers
Classifier: Topic :: Office/Business :: Financial :: Investment
Classifier: Programming Language :: Python :: 3.12
Classifier: Programming Language :: C++
Classifier: Operating System :: Microsoft :: Windows
Classifier: Operating System :: POSIX :: Linux
Classifier: Operating System :: MacOS
Project-URL: Homepage, https://github.com/bbalouki/bbstrader
Project-URL: Download, https://pypi.org/project/bbstrader/
Project-URL: Documentation, https://bbstrader.readthedocs.io/en/latest/
Project-URL: Source Code, https://github.com/bbalouki/bbstrader
Requires-Python: >=3.12
Requires-Dist: beautifulsoup4>=4.13.5
Requires-Dist: colorama>=0.4.6
Requires-Dist: eodhd>=1.0.32
Requires-Dist: exchange_calendars>=4.11.1
Requires-Dist: financetoolkit>=2.0.4
Requires-Dist: ipython>=9.5.0
Requires-Dist: nltk>=3.9.1
Requires-Dist: notify_py>=0.3.43
Requires-Dist: numpy>=2.2.6
Requires-Dist: praw>=7.8.1
Requires-Dist: pybind11>=3.0.1
Requires-Dist: pyfiglet>=1.0.4
Requires-Dist: pyportfolioopt>=1.5.6
Requires-Dist: python-dotenv>=1.1.1
Requires-Dist: python-telegram-bot>=22.3
Requires-Dist: PyYAML>=6.0.2
Requires-Dist: QuantStats>=0.0.77
Requires-Dist: seaborn>=0.13.2
Requires-Dist: spacy>=3.8.11
Requires-Dist: sumy>=0.11.0
Requires-Dist: tabulate>=0.9.0
Requires-Dist: textblob>=0.19.0
Requires-Dist: tweepy>=4.16.0
Requires-Dist: vaderSentiment>=3.3.2
Requires-Dist: yfinance>=0.2.65
Provides-Extra: mt5
Requires-Dist: MetaTrader5; extra == "mt5"
